{
    "kind": "SeldonDeployment",
    "apiVersion": "machinelearning.seldon.io/v1alpha2",
    "metadata": {
        "name": "cifar10",
        "namespace": "default",
        "creationTimestamp": null
    },
    "spec": {
        "name": "cifar10",
        "predictors": [
            {
                "name": "default",
                "graph": {
                    "name": "cifar10-default",
                    "implementation": "TENSORFLOW_SERVER",
                    "endpoint": {
                        "type": "REST"
                    },
                    "modelUri": "gs://seldon-models/alibi-detect/classifier/cifar10/resnet32",
                    "logger": {
                        "url": "http://default-broker",
                        "mode": "all"
                    }
                },
                "componentSpecs": [
                    {
                        "metadata": {
                            "creationTimestamp": "2020-03-16T09:22:57Z"
                        },
                        "spec": {
                            "containers": [
                                {
                                    "name": "cifar10-default",
                                    "resources": {}
                                }
                            ]
                        }
                    }
                ],
                "replicas": 1,
                "engineResources": {},
                "svcOrchSpec": {},
                "traffic": 100,
                "explainer": {
                    "containerSpec": {
                        "name": "",
                        "resources": {}
                    }
                }
            }
        ],
        "annotations": {
            "seldon.io/engine-seldon-log-messages-externally": "true"
        }
    },
    "status": {}
}